bazaar/__init__.py
bazaar/bazaar.py
bazaar-1.0.1.dist-info/LICENSE
bazaar-1.0.1.dist-info/METADATA
bazaar-1.0.1.dist-info/WHEEL
bazaar-1.0.1.dist-info/top_level.txt
bazaar-1.0.1.dist-info/RECORD
