Metadata-Version: 2.1
Name: bazaar
Version: 1.0.1
Summary: Agnostic file storage
Home-page: https://github.com/bmat/bazaar
Author: BMAT developers
Author-email: tv-av@bmat.com
License: UNKNOWN
Download-URL: https://github.com/bmat/bazaar/archive/master.zip
Keywords: storage,s3,ftp,file,mongo,mongodb,fs,filesystem
Platform: UNKNOWN
Classifier: Topic :: Adaptive Technologies
Classifier: Topic :: Software Development
Classifier: Topic :: System
Classifier: Topic :: Utilities
Requires-Dist: fs (==2.4.11)
Requires-Dist: pymongo (<4.0,>=3.4)
Provides-Extra: s3
Requires-Dist: fs-s3fs (==1.1.1) ; extra == 's3'
